metawibele/__init__.py
metawibele/check.py
metawibele/config.py
metawibele/metawibele.py
metawibele/utilities.py
metawibele/Rscripts/maaslin2_utils.R
metawibele/Rscripts/pcl_utils.R
metawibele/characterize/__init__.py
metawibele/characterize/abundance_annotator.py
metawibele/characterize/ddi_DOMINE_ExpAtlas.py
metawibele/characterize/ddi_DOMINE_SIFTS.py
metawibele/characterize/ddi_DOMINE_ann.py
metawibele/characterize/ddi_DOMINE_protein.py
metawibele/characterize/ddi_DOMINE_protein_family.py
metawibele/characterize/denovo_TM_SP.py
metawibele/characterize/finalize_annotation.py
metawibele/characterize/interproscan_annotator.py
metawibele/characterize/interproscan_pfam_protein_family.py
metawibele/characterize/interproscan_phobius_protein_family.py
metawibele/characterize/interproscan_protein.py
metawibele/characterize/interproscan_protein_family.py
metawibele/characterize/interproscan_signalp_protein_family.py
metawibele/characterize/interproscan_tmhmm_protein_family.py
metawibele/characterize/maaslin2.py
metawibele/characterize/maaslin2_annotator.py
metawibele/characterize/maaslin2_collection.py
metawibele/characterize/maaslin2_summary.py
metawibele/characterize/metadata_format.py
metawibele/characterize/msp_protein_family.py
metawibele/characterize/mspminer_msp.py
metawibele/characterize/mspminer_msp_taxonomy_annotation.py
metawibele/characterize/mspminer_msp_uniref_annotation.py
metawibele/characterize/mspminer_protein.py
metawibele/characterize/mspminer_protein_family.py
metawibele/characterize/mspminer_protein_family_taxonomy.py
metawibele/characterize/pfam2go.py
metawibele/characterize/psortb_annotator.py
metawibele/characterize/psortb_protein.py
metawibele/characterize/psortb_protein_family.py
metawibele/characterize/sum_to_protein_family_abundance.py
metawibele/characterize/summary_all_annotation.py
metawibele/characterize/summary_function_annotation.py
metawibele/characterize/summary_protein_family_uniref_annotation.py
metawibele-0.4.8.dist-info/LICENSE
metawibele-0.4.8.dist-info/METADATA
metawibele-0.4.8.dist-info/WHEEL
metawibele-0.4.8.dist-info/entry_points.txt
metawibele-0.4.8.dist-info/top_level.txt
metawibele-0.4.8.dist-info/RECORD
