Metadata-Version: 2.1
Name: metawibele
Version: 0.4.8
Summary: MetaWIBELE: Workflow to Identify novel Bioactive Elements in microbiome
Home-page: https://github.com/biobakery/metawibele
Author: MetaWIBELE Development Team
Author-email: zhangyc201211@gmail.com
License: MIT
Keywords: microbial,microbiome,bioinformatics,microbiology,metagenomic,metatranscriptomic,gene catalog,bioactive,assembly,metawibele,anadama2
Platform: Linux
Platform: MacOS
Classifier: Programming Language :: Python
Classifier: Development Status :: 5 - Production/Stable
Classifier: Environment :: Console
Classifier: Operating System :: MacOS
Classifier: Operating System :: Unix
Classifier: Programming Language :: Python :: 3.6
Classifier: Topic :: Scientific/Engineering :: Bio-Informatics
